jira_veya/__init__.py
jira_veya/jira_veya.py
jira_veya-0.0.2.dist-info/METADATA
jira_veya-0.0.2.dist-info/WHEEL
jira_veya-0.0.2.dist-info/licenses/LICENSE
jira_veya-0.0.2.dist-info/RECORD
