Metadata-Version: 2.4
Name: jira_veya
Version: 0.0.2
Summary: collection of biblical humans and their family relations
Author-email: Veya <kamit@veya.in>
License-File: LICENSE
Classifier: License :: OSI Approved :: GNU General Public License v3 (GPLv3)
Classifier: Operating System :: OS Independent
Classifier: Programming Language :: Python :: 3
Requires-Python: >=3.0
